client/__init__.py
client/launcher_for_ubuntu.py
client/launcher_for_windows.py
client/start_client.py
client/client/__init__.py
client/client/client_db.py
client/client/login_dialog.py
client/client/login_dialog_ui.py
client/client/main_window.py
client/client/main_window_ui.py
client/client/transport.py
client/common/__init__.py
client/common/errors.py
client/common/globals.py
client/common/utils.py
client/log/__init__.py
client/log/client_log_config.py
client/log/decorator.py
py_yuwinzer_client-0.3.14.dist-info/METADATA
py_yuwinzer_client-0.3.14.dist-info/WHEEL
py_yuwinzer_client-0.3.14.dist-info/top_level.txt
py_yuwinzer_client-0.3.14.dist-info/RECORD
